gasofo/__init__.py
gasofo/convenience.py
gasofo/dep_parser.py
gasofo/discoverable.py
gasofo/domain.py
gasofo/exceptions.py
gasofo/ports.py
gasofo/service.py
gasofo/service_needs.py
gasofo/testing/__init__.py
gasofo/testing/adapters.py
gasofo/testing/patchers.py
gasofo/testing/testcase_base.py
gasofo-2.0.0.dist-info/METADATA
gasofo-2.0.0.dist-info/WHEEL
gasofo-2.0.0.dist-info/top_level.txt
gasofo-2.0.0.dist-info/RECORD
