Metadata-Version: 2.1
Name: gasofo
Version: 2.0.0
Summary: Qwil's hexagonal architecture framework
Home-page: https://github.com/QwilApp/gasofo
Author: Shawn Chin
Author-email: shawn@qwil.io
License: UNKNOWN
Platform: UNKNOWN
Classifier: Programming Language :: Python :: 3.9
Classifier: License :: OSI Approved :: MIT License
Classifier: Operating System :: OS Independent
Requires-Python: >=3.6
